diaspora_event_sdk/__init__.py
diaspora_event_sdk/version.py
diaspora_event_sdk/sdk/__init__.py
diaspora_event_sdk/sdk/_environments.py
diaspora_event_sdk/sdk/aws_iam_msk.py
diaspora_event_sdk/sdk/client.py
diaspora_event_sdk/sdk/decorators.py
diaspora_event_sdk/sdk/kafka_client.py
diaspora_event_sdk/sdk/web_client.py
diaspora_event_sdk/sdk/botocore/__init__.py
diaspora_event_sdk/sdk/botocore/auth.py
diaspora_event_sdk/sdk/botocore/awsrequest.py
diaspora_event_sdk/sdk/botocore/compat.py
diaspora_event_sdk/sdk/botocore/credentials.py
diaspora_event_sdk/sdk/botocore/exceptions.py
diaspora_event_sdk/sdk/botocore/utils.py
diaspora_event_sdk/sdk/login_manager/__init__.py
diaspora_event_sdk/sdk/login_manager/client_login.py
diaspora_event_sdk/sdk/login_manager/decorators.py
diaspora_event_sdk/sdk/login_manager/globus_auth.py
diaspora_event_sdk/sdk/login_manager/login_flow.py
diaspora_event_sdk/sdk/login_manager/manager.py
diaspora_event_sdk/sdk/login_manager/protocol.py
diaspora_event_sdk/sdk/login_manager/tokenstore.py
diaspora_event_sdk/sdk/utils/__init__.py
diaspora_event_sdk/sdk/utils/uuid_like.py
tests/__init__.py
tests/unit/apis_test.py
tests/unit/client_test.py
diaspora_event_sdk-0.4.1.dist-info/LICENSE
diaspora_event_sdk-0.4.1.dist-info/METADATA
diaspora_event_sdk-0.4.1.dist-info/WHEEL
diaspora_event_sdk-0.4.1.dist-info/top_level.txt
diaspora_event_sdk-0.4.1.dist-info/RECORD
