Metadata-Version: 2.1
Name: diaspora-event-sdk
Version: 0.4.1
Summary: Diaspora Event Fabric SDK
Home-page: https://github.com/globus-labs/diaspora-event-sdk
License: Apache 2.0
Classifier: Development Status :: 5 - Production/Stable
Classifier: Intended Audience :: Developers
Classifier: License :: OSI Approved :: Apache Software License
Classifier: Programming Language :: Python
Classifier: Programming Language :: Python :: 3.7
Classifier: Programming Language :: Python :: 3.8
Classifier: Programming Language :: Python :: 3.9
Classifier: Programming Language :: Python :: 3.10
Classifier: Programming Language :: Python :: 3.11
Classifier: Programming Language :: Python :: 3.12
License-File: LICENSE
Requires-Dist: globus-sdk<4,>=3.20.1
Provides-Extra: kafka-python
Requires-Dist: kafka-python; extra == "kafka-python"
Provides-Extra: test
Requires-Dist: pytest; extra == "test"
Requires-Dist: pytest-cov; extra == "test"
Requires-Dist: coverage; extra == "test"
Requires-Dist: mypy; extra == "test"
Requires-Dist: tox; extra == "test"
Requires-Dist: check-manifest; extra == "test"
Requires-Dist: pre-commit; extra == "test"
